ilmn/pelops/__init__.py
ilmn/pelops/cli.py
ilmn/pelops/defaults.py
ilmn/pelops/entities.py
ilmn/pelops/notifications.py
ilmn/pelops/repositories.py
ilmn/pelops/request_models.py
ilmn/pelops/result_models.py
ilmn/pelops/selectors.py
ilmn/pelops/stores.py
ilmn/pelops/callers/__init__.py
ilmn/pelops/callers/caller_factories.py
ilmn/pelops/callers/read_callers.py
ilmn/pelops/callers/rearrangement_callers.py
ilmn/pelops/callers/region_callers.py
ilmn/pelops/callers/region_pair_callers.py
ilmn/pelops/callers/sorters.py
ilmn/pelops/factories/__init__.py
ilmn/pelops/factories/interactor_factories.py
ilmn/pelops/infrastructure/__init__.py
ilmn/pelops/infrastructure/blacklist_region_repository.py
ilmn/pelops/infrastructure/log_notifications.py
ilmn/pelops/infrastructure/pysam_repositories.py
ilmn/pelops/interactors/__init__.py
ilmn/pelops/interactors/classify_interactor.py
ilmn/pelops/ui/__init__.py
ilmn/pelops/ui/cli/__init__.py
ilmn/pelops/ui/cli/controllers.py
ilmn/pelops/ui/cli/presenters/__init__.py
ilmn/pelops/ui/cli/presenters/cli_presenter.py
ilmn/pelops/ui/cli/presenters/introspection.py
ilmn/pelops/ui/cli/presenters/presenter_factories.py
ilmn/pelops/ui/cli/presenters/views/__init__.py
ilmn/pelops/ui/cli/presenters/views/json_classification_export_view.py
ilmn/pelops/ui/cli/presenters/views/pysam_segment_export_view.py
ilmn/pelops/ui/cli/presenters/views/view_factories.py
ilmn_pelops-0.8.0.dist-info/AUTHORS.md
ilmn_pelops-0.8.0.dist-info/LICENSE
ilmn_pelops-0.8.0.dist-info/METADATA
ilmn_pelops-0.8.0.dist-info/WHEEL
ilmn_pelops-0.8.0.dist-info/entry_points.txt
ilmn_pelops-0.8.0.dist-info/top_level.txt
ilmn_pelops-0.8.0.dist-info/RECORD
