Metadata-Version: 2.1
Name: ilmn-pelops
Version: 0.8.0
Summary: Dedicated caller for DUX4 rearrangements from whole genome sequencing data.
Author-email: Stefano Berri <sberri@illumina.com>, Pascal Grobecker <pgrobecker@illumina.com>, Kai Jie Chow <kchow@illumina.com>, Martina Mijuskovic <mmijuskovic@illumina.com>
Maintainer-email: Stefano Berri <sberri@illumina.com>, Kai Jie Chow <kchow@illumina.com>
License: PolyForm Strict License 1.0.0
Project-URL: Repository, https://github.com/Illumina/Pelops
Keywords: DUX4,acute lymphoblastic leukaemia,whole-genome sequencing,IGH::DUX4 rearrangements
Classifier: Development Status :: 4 - Beta
Classifier: Intended Audience :: Developers
Classifier: Intended Audience :: Science/Research
Classifier: Environment :: Console
Classifier: Natural Language :: English
Classifier: Programming Language :: Python :: 3.7
Classifier: Programming Language :: Python :: 3.8
Classifier: Programming Language :: Python :: 3.9
Classifier: Programming Language :: Python :: 3.10
Classifier: Programming Language :: Python :: 3.11
Classifier: Programming Language :: Python :: 3.12
Classifier: Operating System :: MacOS :: MacOS X
Classifier: Operating System :: POSIX :: Linux
Classifier: Topic :: Scientific/Engineering :: Bio-Informatics
Requires-Python: >=3.7
License-File: LICENSE
License-File: AUTHORS.md
Requires-Dist: pysam
Requires-Dist: importlib-metadata
Requires-Dist: typing-extensions
